{"cameraMode":{"drawMode":0,"name":"Shaded","section":"Shading Mode"},"sceneLighting":false,"audioPlay":false,"sceneViewState":{"m_AlwaysRefresh":false,"showFog":true,"showSkybox":false,"showFlares":true,"showImageEffects":true,"showParticleSystems":true,"showVisualEffectGraphs":true,"m_FxEnabled":true},"in2DMode":false,"pivot":{"x":-7.433672904968262,"y":5.673132419586182,"z":-203.10787963867188},"rotation":{"x":-0.14100825786590577,"y":0.6933642625808716,"z":0.1413780152797699,"w":0.6925576329231262},"size":5.733248710632324,"orthographic":false}